helloengland/__init__.py
helloengland/greeting.py
helloengland/cli/sayhelloto.py
helloengland/submodules/repo-greeting-china/README.md
helloengland/submodules/repo-greeting-china/hellochina/__init__.py
helloengland/submodules/repo-greeting-china/hellochina/greeting.py
helloengland/submodules/repo-greeting-korea/README.md
helloengland/submodules/repo-greeting-korea/pyproject.toml
helloengland/submodules/repo-greeting-korea/.git/FETCH_HEAD
helloengland/submodules/repo-greeting-korea/.git/HEAD
helloengland/submodules/repo-greeting-korea/.git/config
helloengland/submodules/repo-greeting-korea/.git/description
helloengland/submodules/repo-greeting-korea/.git/hooks/applypatch-msg.sample
helloengland/submodules/repo-greeting-korea/.git/hooks/commit-msg.sample
helloengland/submodules/repo-greeting-korea/.git/hooks/fsmonitor-watchman.sample
helloengland/submodules/repo-greeting-korea/.git/hooks/post-update.sample
helloengland/submodules/repo-greeting-korea/.git/hooks/pre-applypatch.sample
helloengland/submodules/repo-greeting-korea/.git/hooks/pre-commit.sample
helloengland/submodules/repo-greeting-korea/.git/hooks/pre-merge-commit.sample
helloengland/submodules/repo-greeting-korea/.git/hooks/pre-push.sample
helloengland/submodules/repo-greeting-korea/.git/hooks/pre-rebase.sample
helloengland/submodules/repo-greeting-korea/.git/hooks/pre-receive.sample
helloengland/submodules/repo-greeting-korea/.git/hooks/prepare-commit-msg.sample
helloengland/submodules/repo-greeting-korea/.git/hooks/push-to-checkout.sample
helloengland/submodules/repo-greeting-korea/.git/hooks/update.sample
helloengland/submodules/repo-greeting-korea/.git/info/exclude
helloengland/submodules/repo-greeting-korea/hellokorea/__init__.py
helloengland/submodules/repo-greeting-korea/hellokorea/greeting.py
helloengland/subpackage/humble_greeting.py
helloengland-0.2.2.dist-info/entry_points.txt
helloengland-0.2.2.dist-info/WHEEL
helloengland-0.2.2.dist-info/METADATA
helloengland-0.2.2.dist-info/RECORD
