Metadata-Version: 2.1
Name: helloengland
Version: 0.2.2
Summary: hello world!
Author-email: Janghoo Lee <dlwkdgn1@naver.com>
Requires-Python: >=3.8
Requires-Dist: click
Requires-Dist: pytest ; extra == "dev"
Provides-Extra: dev
